xinfer/__init__.py
xinfer/core.py
xinfer/model_registry.py
xinfer/models.py
xinfer/optional_imports.py
xinfer/serve.py
xinfer/types.py
xinfer/viz.py
xinfer/ollama/__init__.py
xinfer/ollama/llava_phi3.py
xinfer/timm/__init__.py
xinfer/timm/imagenet1k_classes.py
xinfer/timm/load_timm_models.py
xinfer/timm/timm_model.py
xinfer/transformers/__init__.py
xinfer/transformers/blip2.py
xinfer/transformers/florence2.py
xinfer/transformers/joycaption.py
xinfer/transformers/llama32.py
xinfer/transformers/moondream.py
xinfer/transformers/qwen2_vl.py
xinfer/transformers/vision2seq.py
xinfer/transformers/vlrm_blip2.py
xinfer/ultralytics/__init__.py
xinfer/ultralytics/ultralytics_model.py
xinfer/ultralytics/yolov10.py
xinfer/ultralytics/yolov11.py
xinfer/ultralytics/yolov8.py
xinfer/vllm/__init__.py
xinfer/vllm/molmo.py
xinfer/vllm/phi35vision.py
xinfer-0.3.2.dist-info/LICENSE
xinfer-0.3.2.dist-info/METADATA
xinfer-0.3.2.dist-info/WHEEL
xinfer-0.3.2.dist-info/entry_points.txt
xinfer-0.3.2.dist-info/top_level.txt
xinfer-0.3.2.dist-info/RECORD
