Metadata-Version: 2.1
Name: xinfer
Version: 0.3.2
Summary: Framework agnostic computer vision inference. Run 1000+ models by changing only one line of code. Supports models from transformers, timm, ultralytics, vllm, ollama and your custom model.
Author-email: Dickson Neoh <dickson.neoh@gmail.com>
License: Apache Software License 2.0
Project-URL: Homepage, https://github.com/dnth/xinfer
Keywords: xinfer
Classifier: Intended Audience :: Developers
Classifier: License :: OSI Approved :: Apache Software License
Classifier: Natural Language :: English
Classifier: Programming Language :: Python :: 3.10
Classifier: Programming Language :: Python :: 3.11
Classifier: Programming Language :: Python :: 3.12
Requires-Python: >=3.10
License-File: LICENSE
Requires-Dist: loguru
Requires-Dist: rich <14,>=13.9.4
Requires-Dist: requests <3,>=2.32.3
Requires-Dist: pillow <11,>=10.4.0
Requires-Dist: ray[serve] <3,>=2.38.0
Requires-Dist: fastapi <0.116,>=0.115.5
Requires-Dist: timm <2,>=1.0.11
Requires-Dist: gradio <6,>=5.5.0
Requires-Dist: itables <3,>=2.2.3
Requires-Dist: einops <0.9,>=0.8.0
Provides-Extra: all
Requires-Dist: ultralytics ; extra == 'all'
Requires-Dist: transformers ; extra == 'all'
Requires-Dist: vllm ; extra == 'all'
Requires-Dist: ollama ; extra == 'all'
Requires-Dist: accelerate ; extra == 'all'
Requires-Dist: triton ; extra == 'all'
Provides-Extra: ollama
Requires-Dist: ollama ; extra == 'ollama'
Provides-Extra: transformers
Requires-Dist: transformers ; extra == 'transformers'
Requires-Dist: accelerate ; extra == 'transformers'
Provides-Extra: ultralytics
Requires-Dist: ultralytics ; extra == 'ultralytics'
Provides-Extra: vllm
Requires-Dist: vllm ; extra == 'vllm'
Requires-Dist: triton ; extra == 'vllm'
